pydevtools/__init__.py
pydevtools/debug/__init__.py
pydevtools/optimize/__init__.py
pydevtools-0.1.dev0.dist-info/DESCRIPTION.rst
pydevtools-0.1.dev0.dist-info/METADATA
pydevtools-0.1.dev0.dist-info/RECORD
pydevtools-0.1.dev0.dist-info/WHEEL
pydevtools-0.1.dev0.dist-info/metadata.json
pydevtools-0.1.dev0.dist-info/top_level.txt
