Metadata-Version: 2.0
Name: pydevtools
Version: 0.1.dev0
Summary: UNKNOWN
Home-page: UNKNOWN
Author: AndersBallegaard
Author-email: anderstb@hotmail.dk
License: MIT
Platform: UNKNOWN
